aedev/aedev/__init__.py
aedev/aedev/templates/de_spt_namespace-root_de_otf_de_tpl_README.md
aedev_aedev-0.3.27.dist-info/licenses/LICENSE.md
aedev_aedev-0.3.27.dist-info/METADATA
aedev_aedev-0.3.27.dist-info/WHEEL
aedev_aedev-0.3.27.dist-info/top_level.txt
aedev_aedev-0.3.27.dist-info/RECORD
