Metadata-Version: 2.4
Name: aedev_aedev
Version: 0.3.27
Summary: aedev namespace-root: aedev namespace root, providing setup, development and documentation tools/templates for Python projects.
Home-page: https://gitlab.com/aedev-group/aedev_aedev
Author: AndiEcker
Author-email: aecker2@gmail.com
License: GPL-3.0-or-later
Project-URL: Bug Tracker, https://gitlab.com/aedev-group/aedev_aedev/-/issues
Project-URL: Documentation, https://aedev.readthedocs.io/en/latest/_autosummary/aedev.aedev.html
Project-URL: Repository, https://gitlab.com/aedev-group/aedev_aedev
Project-URL: Source, https://aedev.readthedocs.io/en/latest/_modules/aedev/aedev.html
Keywords: configuration,development,environment,productivity
Classifier: Development Status :: 3 - Alpha
Classifier: Natural Language :: English
Classifier: Operating System :: OS Independent
Classifier: Programming Language :: Python
Classifier: Programming Language :: Python :: 3
Classifier: Programming Language :: Python :: 3.9
Classifier: Topic :: Software Development
Classifier: Typing :: Typed
Requires-Python: >=3.9
License-File: LICENSE.md
Provides-Extra: dev
Requires-Dist: aedev_app_tpls; extra == "dev"
Requires-Dist: aedev_namespace_root_tpls; extra == "dev"
Requires-Dist: aedev_project_tpls; extra == "dev"
Requires-Dist: aedev_aedev; extra == "dev"
Requires-Dist: aedev_project_manager; extra == "dev"
Requires-Dist: sphinx; extra == "dev"
Requires-Dist: sphinx-rtd-theme; extra == "dev"
Requires-Dist: sphinx_autodoc_typehints; extra == "dev"
Requires-Dist: sphinx_paramlinks; extra == "dev"
Requires-Dist: ae_dev_ops; extra == "dev"
Requires-Dist: anybadge; extra == "dev"
Requires-Dist: coverage-badge; extra == "dev"
Requires-Dist: aedev_project_manager; extra == "dev"
Requires-Dist: flake8; extra == "dev"
Requires-Dist: mypy; extra == "dev"
Requires-Dist: pylint; extra == "dev"
Requires-Dist: pytest; extra == "dev"
Requires-Dist: pytest-cov; extra == "dev"
Requires-Dist: pytest-django; extra == "dev"
Requires-Dist: typing; extra == "dev"
Requires-Dist: types-setuptools; extra == "dev"
Provides-Extra: docs
Requires-Dist: sphinx; extra == "docs"
Requires-Dist: sphinx-rtd-theme; extra == "docs"
Requires-Dist: sphinx_autodoc_typehints; extra == "docs"
Requires-Dist: sphinx_paramlinks; extra == "docs"
Requires-Dist: ae_dev_ops; extra == "docs"
Provides-Extra: tests
Requires-Dist: anybadge; extra == "tests"
Requires-Dist: coverage-badge; extra == "tests"
Requires-Dist: aedev_project_manager; extra == "tests"
Requires-Dist: flake8; extra == "tests"
Requires-Dist: mypy; extra == "tests"
Requires-Dist: pylint; extra == "tests"
Requires-Dist: pytest; extra == "tests"
Requires-Dist: pytest-cov; extra == "tests"
Requires-Dist: pytest-django; extra == "tests"
Requires-Dist: typing; extra == "tests"
Requires-Dist: types-setuptools; extra == "tests"
Dynamic: author
Dynamic: author-email
Dynamic: classifier
Dynamic: description
Dynamic: description-content-type
Dynamic: home-page
Dynamic: keywords
Dynamic: license
Dynamic: license-file
Dynamic: project-url
Dynamic: provides-extra
Dynamic: requires-python
Dynamic: summary
